packaging_priyal/__init__.py
packaging_priyal/api_dealer.py
packaging_priyal-0.1.dist-info/METADATA
packaging_priyal-0.1.dist-info/WHEEL
packaging_priyal-0.1.dist-info/top_level.txt
packaging_priyal-0.1.dist-info/RECORD
